optimization_benchmarks/__init__.py
optimization_benchmarks/benchmarking.py
optimization_benchmarks/cli.py
optimization_benchmarks/functions.py
optimization_benchmarks/metadata.py
optimization_benchmarks/py.typed
optimization_benchmarks/utils.py
optimization_benchmarks/visualization.py
optimization_benchmarks-0.3.0.dist-info/licenses/LICENSE.md
optimization_benchmarks-0.3.0.dist-info/METADATA
optimization_benchmarks-0.3.0.dist-info/WHEEL
optimization_benchmarks-0.3.0.dist-info/entry_points.txt
optimization_benchmarks-0.3.0.dist-info/top_level.txt
optimization_benchmarks-0.3.0.dist-info/RECORD
