Metadata-Version: 2.4
Name: optimization-benchmarks
Version: 0.3.0
Summary: A comprehensive collection of 55+ mathematical benchmark functions for testing optimization algorithms with visualization and benchmarking utilities
Author-email: AK Rahul <ak-rahul@users.noreply.github.com>
Maintainer-email: AK Rahul <ak-rahul@users.noreply.github.com>
License: MIT
Project-URL: Homepage, https://github.com/ak-rahul/optimization-benchmarks
Project-URL: Repository, https://github.com/ak-rahul/optimization-benchmarks
Project-URL: Bug Tracker, https://github.com/ak-rahul/optimization-benchmarks/issues
Keywords: optimization,benchmark,test-functions,mathematical-optimization,global-optimization,algorithms,machine-learning,numerical-optimization,metaheuristics,visualization,benchmarking
Classifier: Development Status :: 4 - Beta
Classifier: Intended Audience :: Science/Research
Classifier: Intended Audience :: Developers
Classifier: License :: OSI Approved :: MIT License
Classifier: Operating System :: OS Independent
Classifier: Programming Language :: Python :: 3
Classifier: Programming Language :: Python :: 3.9
Classifier: Programming Language :: Python :: 3.10
Classifier: Programming Language :: Python :: 3.11
Classifier: Programming Language :: Python :: 3.12
Classifier: Topic :: Scientific/Engineering
Classifier: Topic :: Scientific/Engineering :: Mathematics
Classifier: Topic :: Scientific/Engineering :: Artificial Intelligence
Classifier: Topic :: Software Development :: Libraries :: Python Modules
Classifier: Typing :: Typed
Requires-Python: >=3.9
License-File: LICENSE.md
Requires-Dist: numpy>=1.20.0
Requires-Dist: tqdm>=4.65.0
Provides-Extra: viz
Requires-Dist: matplotlib>=3.3.0; extra == "viz"
Provides-Extra: dev
Requires-Dist: pytest>=7.0.0; extra == "dev"
Requires-Dist: pytest-cov>=4.0.0; extra == "dev"
Requires-Dist: black>=23.0.0; extra == "dev"
Requires-Dist: flake8>=6.0.0; extra == "dev"
Requires-Dist: mypy>=1.0.0; extra == "dev"
Requires-Dist: isort>=5.12.0; extra == "dev"
Requires-Dist: matplotlib>=3.3.0; extra == "dev"
Requires-Dist: tqdm>=4.65.0; extra == "dev"
Provides-Extra: docs
Requires-Dist: sphinx>=5.0.0; extra == "docs"
Requires-Dist: sphinx-rtd-theme>=1.2.0; extra == "docs"
Provides-Extra: all
Requires-Dist: matplotlib>=3.3.0; extra == "all"
Requires-Dist: tqdm>=4.65.0; extra == "all"
Dynamic: license-file
